jsi/__init__.py
jsi/__main__.py
jsi/cli.py
jsi/client.py
jsi/config/loader.py
jsi/config/solvers.json
jsi/core.py
jsi/output/basic.py
jsi/output/fancy.py
jsi/reaper.py
jsi/server.py
jsi/utils.py
just_solve_it-0.1.2.dist-info/METADATA
just_solve_it-0.1.2.dist-info/WHEEL
just_solve_it-0.1.2.dist-info/entry_points.txt
just_solve_it-0.1.2.dist-info/licenses/LICENSE
just_solve_it-0.1.2.dist-info/RECORD
