Metadata-Version: 2.1
Name: just-solve-it
Version: 0.1.2
Summary: just solve it - a command line tool to run multiple SMT (Satisfiability Modulo Theories) solvers in parallel
Author-Email: karmacoma <karma@a16z.com>, a16z crypto research lab <crypto-research-lab@a16z.com>
Requires-Python: >=3.11
Requires-Dist: pyright>=1.1.378
Requires-Dist: rich>=13.8.1
Requires-Dist: python-daemon>=3.0.1
